{"is_source_file": true, "format": "JavaScript (Node.js)", "description": "A JavaScript source file intended to export middleware components for a Node.js application, currently serving as a placeholder with no actual middleware implemented.", "external_files": [], "external_methods": [], "published": [], "classes": [], "methods": [], "calls": [], "search-terms": ["middleware", "Node.js", "export", "placeholder"], "state": 2, "file_id": 2, "knowledge_revision": 16, "git_revision": "b63b87276f4a842102fb7964ab778dbc416b4039", "ctags": [], "hash": "e9169fe9b751451d433ec5c4d4734b4a", "format-version": 4, "code-base-name": "notes_backend", "filename": "notes_backend/src/middleware/index.js", "revision_history": [{"16": "b63b87276f4a842102fb7964ab778dbc416b4039"}]}